histomicsui/__init__.py
histomicsui/constants.py
histomicsui/handlers.py
histomicsui/webroot.mako
histomicsui/models/__init__.py
histomicsui/models/aperio.py
histomicsui/models/case.py
histomicsui/models/cohort.py
histomicsui/models/image.py
histomicsui/models/meta.py
histomicsui/models/pathology.py
histomicsui/models/slide.py
histomicsui/rest/__init__.py
histomicsui/rest/aperio.py
histomicsui/rest/hui_resource.py
histomicsui/rest/image_browse_resource.py
histomicsui/rest/system.py
histomicsui/rest/tcga.py
histomicsui/web_client/app.js
histomicsui/web_client/events.js
histomicsui/web_client/index.js
histomicsui/web_client/main.js
histomicsui/web_client/package.json
histomicsui/web_client/router.js
histomicsui/web_client/routes.js
histomicsui/web_client/webpack.helper.js
histomicsui/web_client/collections/StyleCollection.js
histomicsui/web_client/collections/UserCollection.js
histomicsui/web_client/collections/index.js
histomicsui/web_client/dialogs/confirmDialog.js
histomicsui/web_client/dialogs/editElement.js
histomicsui/web_client/dialogs/editRegionOfInterest.js
histomicsui/web_client/dialogs/editStyleGroups.js
histomicsui/web_client/dialogs/index.js
histomicsui/web_client/dialogs/metadataPlot.js
histomicsui/web_client/dialogs/openAnnotatedImage.js
histomicsui/web_client/dialogs/openImage.js
histomicsui/web_client/dialogs/saveAnnotation.js
histomicsui/web_client/models/StyleModel.js
histomicsui/web_client/models/index.js
histomicsui/web_client/panels/AnnotationSelector.js
histomicsui/web_client/panels/DrawWidget.js
histomicsui/web_client/panels/FrameSelectorWidget.js
histomicsui/web_client/panels/MetadataPlot.js
histomicsui/web_client/panels/MetadataWidget.js
histomicsui/web_client/panels/OverviewWidget.js
histomicsui/web_client/panels/RegionSelector.js
histomicsui/web_client/panels/ZoomWidget.js
histomicsui/web_client/panels/index.js
histomicsui/web_client/static/favicon.png
histomicsui/web_client/stylesheets/body/configView.styl
histomicsui-1.7.2.dist-info/licenses/LICENSE
histomicsui-1.7.2.dist-info/licenses/NOTICE
histomicsui-1.7.2.dist-info/METADATA
histomicsui-1.7.2.dist-info/WHEEL
histomicsui-1.7.2.dist-info/entry_points.txt
histomicsui-1.7.2.dist-info/top_level.txt
histomicsui-1.7.2.dist-info/RECORD
