Metadata-Version: 2.4
Name: histomicsui
Version: 1.7.2
Summary: Organize, visualize, and analyze histology images.
Home-page: https://github.com/DigitalSlideArchive/histomicsui
Author: Kitware, Inc.
Author-email: kitware@kitware.com
License: Apache Software License 2.0
Keywords: girder-plugin,histomicsui
Classifier: Development Status :: 5 - Production/Stable
Classifier: License :: OSI Approved :: Apache Software License
Classifier: Natural Language :: English
Classifier: Programming Language :: Python :: 3
Classifier: Programming Language :: Python :: 3.8
Classifier: Programming Language :: Python :: 3.9
Classifier: Programming Language :: Python :: 3.10
Classifier: Programming Language :: Python :: 3.11
Classifier: Programming Language :: Python :: 3.12
Classifier: Programming Language :: Python :: 3.13
Requires-Python: >=3.8
License-File: LICENSE
License-File: NOTICE
Requires-Dist: girder-large-image-annotation>=1.32.8
Requires-Dist: girder-slicer-cli-web[girder]>=1.4.0
Requires-Dist: cachetools
Requires-Dist: orjson
Provides-Extra: analysis
Dynamic: author
Dynamic: author-email
Dynamic: classifier
Dynamic: description
Dynamic: description-content-type
Dynamic: home-page
Dynamic: keywords
Dynamic: license
Dynamic: license-file
Dynamic: provides-extra
Dynamic: requires-dist
Dynamic: requires-python
Dynamic: summary
